<?xml version="1.0" encoding="utf-8"?>
<root>
	<crew>
		<commander/>
		<gunner/>
		<radioman/>
		<driver/>
		<loader/>
		<radioman/>
	</crew>
	<speedLimits>
		<forward>45</forward>
		<backward>20</backward>
	</speedLimits>
	<invisibility>
		<moving>
			0.153
			<!--BW_String-->
		</moving>
		<still>
			0.204
			<!--BW_String-->
		</still>
		<camouflageBonus>
			0.03
			<!--BW_String-->
		</camouflageBonus>
		<camouflageNetBonus>
			0.1
			<!--BW_String-->
		</camouflageNetBonus>
		<firePenalty>
			0.306
			<!--BW_String-->
		</firePenalty>
	</invisibility>
	<repairCost>
		3.80
		<!--BW_String-->
	</repairCost>
	<crewXpFactor>
		1.0
		<!--BW_String-->
	</crewXpFactor>
	<camouflage>
		<priceFactor>
			0.8
			<!--BW_String-->
		</priceFactor>
		<tiling>1 1 0 0</tiling>
		<exclusionMask>vehicles/russian/R06_T-28/T-28_hull_01_AM.dds</exclusionMask>
	</camouflage>
	<hull>
		<armor>
			<armor_1>30</armor_1>
			<armor_2>15</armor_2>
			<armor_3>20</armor_3>
			<armor_4>20</armor_4>
			<armor_5>15</armor_5>
			<armor_6>10</armor_6>
			<armor_7>
				10
				<vehicleDamageFactor>
					0.0
					<!--BW_String-->
				</vehicleDamageFactor>
			</armor_7>
			<armor_8>0</armor_8>
		</armor>
		<primaryArmor>armor_1 armor_3 armor_4</primaryArmor>
		<weight>7580</weight>
		<maxHealth>256</maxHealth>
		<ammoBayHealth>
			<maxHealth>110</maxHealth>
			<maxRegenHealth>75</maxRegenHealth>
			<repairCost>
				1.0
				<!--BW_String-->
			</repairCost>
		</ammoBayHealth>
		<models>
			<undamaged>vehicles/russian/R06_T-28/normal/lod0/Hull.model</undamaged>
			<destroyed>vehicles/russian/R06_T-28/crash/lod0/Hull.model</destroyed>
			<exploded>vehicles/russian/R06_T-28/crash/lod0/Hull.model</exploded>
		</models>
		<swinging>
			<lodDist>FAR</lodDist>
			<pitchParams>
				0.30 32.00 0.38 1.00 0.06 0.34
				<!--BW_String-->
			</pitchParams>
			<rollParams>
				1.00 0.30 32.00 0.38 1.00 0.06 0.34
				<!--BW_String-->
			</rollParams>
			<sensitivityToImpulse>
				0.78
				<!--BW_String-->
			</sensitivityToImpulse>
		</swinging>
		<exhaust>
			<pixie>gas_large</pixie>
			<nodes>HP_Track_Exhaus_1 HP_Track_Exhaus_2</nodes>
		</exhaust>
		<turretPositions>
			<turret>
				0.000000 0.714107 0.66577
				<!--BW_String-->
			</turret>
		</turretPositions>
		<hitTester>
			<collisionModelServer>vehicles/russian/R06_T-28/collision/Hull.model</collisionModelServer>
			<collisionModelClient>vehicles/russian/R06_T-28/collision_client/Hull.model</collisionModelClient>
		</hitTester>
		<emblemSlots>
			<clan>
				<rayStart>
					-0.0158645 0.288189 2.87491
					<!--BW_String-->
				</rayStart>
				<rayEnd>
					-0.0158645 0.104466 2.79588
					<!--BW_String-->
				</rayEnd>
				<rayUp>
					0.000000 0.000000 -1
					<!--BW_String-->
				</rayUp>
				<size>
					0.28
					<!--BW_String-->
				</size>
				<hideIfDamaged>false</hideIfDamaged>
			</clan>
			<inscription>
				<rayStart>
					-1.48035 0.512885 0.106598
					<!--BW_String-->
				</rayStart>
				<rayEnd>
					-1.28035 0.512885 0.106598
					<!--BW_String-->
				</rayEnd>
				<rayUp>
					0.000000 1 0.000000
					<!--BW_String-->
				</rayUp>
				<size>
					0.74
					<!--BW_String-->
				</size>
				<hideIfDamaged>false</hideIfDamaged>
			</inscription>
			<inscription>
				<rayStart>
					1.48035 0.530132 0.124393
					<!--BW_String-->
				</rayStart>
				<rayEnd>
					1.28035 0.530132 0.124393
					<!--BW_String-->
				</rayEnd>
				<rayUp>
					0.000000 1 0.000000
					<!--BW_String-->
				</rayUp>
				<size>
					0.74
					<!--BW_String-->
				</size>
				<hideIfDamaged>true</hideIfDamaged>
			</inscription>
		</emblemSlots>
		<hangarShadowTexture>vehicles/russian/R06_T-28/T-28_HangarShadowMap.dds</hangarShadowTexture>
		<camouflage>
			<tiling>
				2.44 2.44 0.000000 0.000000
				<!--BW_String-->
			</tiling>
		</camouflage>
	</hull>
	<chassis>
		<T-28_0>
			<userString>#ussr_vehicles:T-28_0</userString>
			<tags/>
			<level>3</level>
			<price>
				2270.0
				<!--BW_String-->
			</price>
			<unlocks>
				<chassis>
					T-28_A
					<cost>1220</cost>
				</chassis>
			</unlocks>
			<armor>
				<leftTrack>20</leftTrack>
				<rightTrack>20</rightTrack>
			</armor>
			<weight>5160</weight>
			<maxLoad>18900</maxLoad>
			<terrainResistance>
				1.2 1.5 2.3
				<!--BW_String-->
			</terrainResistance>
			<brakeForce>34500</brakeForce>
			<rotationIsAroundCenter>false</rotationIsAroundCenter>
			<rotationSpeed>35</rotationSpeed>
			<shotDispersionFactors>
				<vehicleMovement>
					0.25
					<!--BW_String-->
				</vehicleMovement>
				<vehicleRotation>
					0.25
					<!--BW_String-->
				</vehicleRotation>
			</shotDispersionFactors>
			<bulkHealthFactor>
				3.0
				<!--BW_String-->
			</bulkHealthFactor>
			<maxHealth>70</maxHealth>
			<maxRegenHealth>55</maxRegenHealth>
			<repairCost>
				5.0
				<!--BW_String-->
			</repairCost>
			<models>
				<undamaged>vehicles/russian/R06_T-28/normal/lod0/Chassis.model</undamaged>
				<destroyed>vehicles/russian/R06_T-28/crash/lod0/Chassis.model</destroyed>
				<exploded>vehicles/russian/R06_T-28/crash/lod0/Chassis.model</exploded>
			</models>
			<traces>
				<lodDist>FAR</lodDist>
				<bufferPrefs>mediumTank</bufferPrefs>
				<textureSet>ussr_01</textureSet>
				<size>
					0.4 0.46
					<!--BW_String-->
				</size>
			</traces>
			<tracks>
				<lodDist>MEDIUM_TRACK</lodDist>
				<leftMaterial>track_mat_L_skinned</leftMaterial>
				<rightMaterial>track_mat_R_skinned</rightMaterial>
				<textureScale>-3</textureScale>
			</tracks>
			<wheels>
				<lodDist>MEDIUM</lodDist>
				<group>
					<isLeft>true</isLeft>
					<template>W_L</template>
					<radius>
						0.19
						<!--BW_String-->
					</radius>
					<startIndex>0</startIndex>
					<count>12</count>
				</group>
				<group>
					<isLeft>false</isLeft>
					<template>W_R</template>
					<radius>
						0.19
						<!--BW_String-->
					</radius>
					<startIndex>0</startIndex>
					<count>12</count>
				</group>
				<wheel>
					<isLeft>true</isLeft>
					<isLeading>true</isLeading>
					<name>WD_L0</name>
					<radius>
						0.42
						<!--BW_String-->
					</radius>
					<syncAngle>
						21.1765
						<!--BW_String-->
					</syncAngle>
				</wheel>
				<group>
					<isLeft>true</isLeft>
					<template>WD_L</template>
					<radius>
						0.16
						<!--BW_String-->
					</radius>
					<startIndex>1</startIndex>
					<count>4</count>
				</group>
				<wheel>
					<isLeft>true</isLeft>
					<isLeading>true</isLeading>
					<name>WD_L5</name>
					<radius>
						0.425
						<!--BW_String-->
					</radius>
					<syncAngle>
						21.1765
						<!--BW_String-->
					</syncAngle>
				</wheel>
				<wheel>
					<isLeft>false</isLeft>
					<isLeading>true</isLeading>
					<name>WD_R0</name>
					<radius>
						0.42
						<!--BW_String-->
					</radius>
					<syncAngle>
						21.1765
						<!--BW_String-->
					</syncAngle>
				</wheel>
				<group>
					<isLeft>false</isLeft>
					<template>WD_R</template>
					<radius>
						0.16
						<!--BW_String-->
					</radius>
					<startIndex>1</startIndex>
					<count>4</count>
				</group>
				<wheel>
					<isLeft>false</isLeft>
					<isLeading>true</isLeading>
					<name>WD_R5</name>
					<radius>
						0.425
						<!--BW_String-->
					</radius>
					<syncAngle>
						21.1765
						<!--BW_String-->
					</syncAngle>
				</wheel>
			</wheels>
			<drivingWheels>WD_L0 WD_L5</drivingWheels>
			<effects>
				<lodDist>MEDIUM</lodDist>
				<dust>mediumTankDust</dust>
				<mud>mediumTankMud</mud>
			</effects>
			<wwsoundPC>treads_type_pc</wwsoundPC>
			<wwsoundNPC>trds_med_npc</wwsoundNPC>
			<hullPosition>
				0.000000 1.1442 0.000000
				<!--BW_String-->
			</hullPosition>
			<hitTester>
				<collisionModelServer>vehicles/russian/R06_T-28/collision/Chassis.model</collisionModelServer>
				<collisionModelClient>vehicles/russian/R06_T-28/collision_client/Chassis.model</collisionModelClient>
			</hitTester>
			<topRightCarryingPoint>
				1.23882 2.5897
				<!--BW_String-->
			</topRightCarryingPoint>
			<maxClimbAngle>25</maxClimbAngle>
			<navmeshGirth>
				6.0
				<!--BW_String-->
			</navmeshGirth>
			<AODecals>
				<decal>
					<transform>
						<row0>3.935060 0.000000 0.000000</row0>
						<row1>0.000000 1.758900 0.000000</row1>
						<row2>-0.000000 0.000000 9.627260</row2>
						<row3>-0.000000 0.000000 0.000000</row3>
					</transform>
				</decal>
			</AODecals>
			<groundNodes>
				<group>
					<template>Track_L</template>
					<startIndex>0</startIndex>
					<count>12</count>
					<isLeft>true</isLeft>
					<minOffset>
						-0.1
						<!--BW_String-->
					</minOffset>
					<maxOffset>
						0.07
						<!--BW_String-->
					</maxOffset>
				</group>
				<group>
					<template>Track_R</template>
					<startIndex>0</startIndex>
					<count>12</count>
					<isLeft>false</isLeft>
					<minOffset>
						-0.1
						<!--BW_String-->
					</minOffset>
					<maxOffset>
						0.07
						<!--BW_String-->
					</maxOffset>
				</group>
			</groundNodes>
			<splineDesc>
				<segmentModelLeft>vehicles/russian/R06_T-28/track/segment.model</segmentModelLeft>
				<segmentModelRight>vehicles/russian/R06_T-28/track/segment.model</segmentModelRight>
				<left>vehicles/russian/R06_T-28/track/left.track</left>
				<right>vehicles/russian/R06_T-28/track/right.track</right>
				<segmentLength>
					0.132
					<!--BW_String-->
				</segmentLength>
				<segmentOffset>
					0.228
					<!--BW_String-->
				</segmentOffset>
				<lodDist>MEDIUM</lodDist>
				<atlas>
					<UTiles>1</UTiles>
					<VTiles>1</VTiles>
				</atlas>
			</splineDesc>
			<trackNodes>
				<enable>true</enable>
				<linkBones>false</linkBones>
				<maxAmplitude>
					0.015
					<!--BW_String-->
				</maxAmplitude>
				<maxOffset>
					0.01
					<!--BW_String-->
				</maxOffset>
				<gravity>-9</gravity>
				<elasticity>757</elasticity>
				<damping>2</damping>
				<forwardElastK>1</forwardElastK>
				<backwardElastK>1</backwardElastK>
				<offset>0.000000</offset>
				<node>
					<isLeft>true</isLeft>
					<name>Track_VT_L0</name>
					<forwardElastK>
						0.85
						<!--BW_String-->
					</forwardElastK>
					<backwardElastK>
						1.6
						<!--BW_String-->
					</backwardElastK>
					<offset>
						-0.099
						<!--BW_String-->
					</offset>
				</node>
				<node>
					<isLeft>false</isLeft>
					<name>Track_VT_R0</name>
					<forwardElastK>
						0.85
						<!--BW_String-->
					</forwardElastK>
					<backwardElastK>
						1.6
						<!--BW_String-->
					</backwardElastK>
					<offset>
						-0.099
						<!--BW_String-->
					</offset>
				</node>
				<node>
					<isLeft>true</isLeft>
					<name>Track_VT_L1</name>
					<forwardElastK>
						0.83
						<!--BW_String-->
					</forwardElastK>
					<backwardElastK>2</backwardElastK>
					<offset>
						-0.027
						<!--BW_String-->
					</offset>
				</node>
				<node>
					<isLeft>true</isLeft>
					<name>Track_VT_L2</name>
					<forwardElastK>
						0.8
						<!--BW_String-->
					</forwardElastK>
					<backwardElastK>
						2.5
						<!--BW_String-->
					</backwardElastK>
					<offset>
						-0.039
						<!--BW_String-->
					</offset>
				</node>
				<node>
					<isLeft>true</isLeft>
					<name>Track_VT_L3</name>
					<forwardElastK>
						0.8
						<!--BW_String-->
					</forwardElastK>
					<backwardElastK>3</backwardElastK>
					<offset>
						-0.044
						<!--BW_String-->
					</offset>
				</node>
				<node>
					<isLeft>true</isLeft>
					<name>Track_VT_L4</name>
					<elasticity>1105</elasticity>
					<forwardElastK>
						0.8
						<!--BW_String-->
					</forwardElastK>
					<backwardElastK>
						3.5
						<!--BW_String-->
					</backwardElastK>
					<offset>
						-0.099
						<!--BW_String-->
					</offset>
				</node>
				<node>
					<isLeft>false</isLeft>
					<name>Track_VT_R1</name>
					<forwardElastK>
						0.83
						<!--BW_String-->
					</forwardElastK>
					<backwardElastK>2</backwardElastK>
					<offset>
						-0.027
						<!--BW_String-->
					</offset>
				</node>
				<node>
					<isLeft>false</isLeft>
					<name>Track_VT_R2</name>
					<forwardElastK>
						0.8
						<!--BW_String-->
					</forwardElastK>
					<backwardElastK>
						2.5
						<!--BW_String-->
					</backwardElastK>
					<offset>
						-0.039
						<!--BW_String-->
					</offset>
				</node>
				<node>
					<isLeft>false</isLeft>
					<name>Track_VT_R3</name>
					<forwardElastK>
						0.8
						<!--BW_String-->
					</forwardElastK>
					<backwardElastK>3</backwardElastK>
					<offset>
						-0.044
						<!--BW_String-->
					</offset>
				</node>
				<node>
					<isLeft>false</isLeft>
					<name>Track_VT_R4</name>
					<elasticity>1105</elasticity>
					<forwardElastK>
						0.8
						<!--BW_String-->
					</forwardElastK>
					<backwardElastK>
						3.5
						<!--BW_String-->
					</backwardElastK>
				</node>
				<node>
					<isLeft>true</isLeft>
					<name>Track_VD_L0</name>
					<forwardElastK>
						1.13
						<!--BW_String-->
					</forwardElastK>
					<backwardElastK>
						1.5
						<!--BW_String-->
					</backwardElastK>
					<offset>
						-0.03
						<!--BW_String-->
					</offset>
				</node>
				<node>
					<isLeft>false</isLeft>
					<name>Track_VD_R0</name>
					<forwardElastK>
						0.88
						<!--BW_String-->
					</forwardElastK>
					<backwardElastK>
						1.5
						<!--BW_String-->
					</backwardElastK>
					<offset>
						-0.03
						<!--BW_String-->
					</offset>
				</node>
				<node>
					<isLeft>true</isLeft>
					<name>Track_VD_L1</name>
					<forwardElastK>
						2.05
						<!--BW_String-->
					</forwardElastK>
					<backwardElastK>
						1.39
						<!--BW_String-->
					</backwardElastK>
					<offset>
						-0.03
						<!--BW_String-->
					</offset>
				</node>
				<node>
					<isLeft>false</isLeft>
					<name>Track_VD_R1</name>
					<forwardElastK>
						2.05
						<!--BW_String-->
					</forwardElastK>
					<backwardElastK>
						0.8
						<!--BW_String-->
					</backwardElastK>
					<offset>
						-0.03
						<!--BW_String-->
					</offset>
				</node>
			</trackNodes>
			<trackThickness>0.000000</trackThickness>
		</T-28_0>
		<T-28_A>
			<userString>#ussr_vehicles:T-28_A</userString>
			<tags/>
			<level>4</level>
			<price>
				5250.0
				<!--BW_String-->
			</price>
			<armor>
				<leftTrack>20</leftTrack>
				<rightTrack>20</rightTrack>
			</armor>
			<weight>5300</weight>
			<maxLoad>32300</maxLoad>
			<terrainResistance>
				1.1 1.3 2.1
				<!--BW_String-->
			</terrainResistance>
			<brakeForce>35500</brakeForce>
			<rotationIsAroundCenter>false</rotationIsAroundCenter>
			<rotationSpeed>40</rotationSpeed>
			<shotDispersionFactors>
				<vehicleMovement>
					0.23
					<!--BW_String-->
				</vehicleMovement>
				<vehicleRotation>
					0.23
					<!--BW_String-->
				</vehicleRotation>
			</shotDispersionFactors>
			<bulkHealthFactor>
				3.0
				<!--BW_String-->
			</bulkHealthFactor>
			<maxHealth>80</maxHealth>
			<maxRegenHealth>60</maxRegenHealth>
			<repairCost>
				5.0
				<!--BW_String-->
			</repairCost>
			<models>
				<undamaged>vehicles/russian/R06_T-28/normal/lod0/Chassis.model</undamaged>
				<destroyed>vehicles/russian/R06_T-28/crash/lod0/Chassis.model</destroyed>
				<exploded>vehicles/russian/R06_T-28/crash/lod0/Chassis.model</exploded>
			</models>
			<traces>
				<lodDist>FAR</lodDist>
				<bufferPrefs>mediumTank</bufferPrefs>
				<textureSet>ussr_01</textureSet>
				<size>
					0.4 0.46
					<!--BW_String-->
				</size>
			</traces>
			<tracks>
				<lodDist>MEDIUM_TRACK</lodDist>
				<leftMaterial>track_mat_L_skinned</leftMaterial>
				<rightMaterial>track_mat_R_skinned</rightMaterial>
				<textureScale>-3</textureScale>
			</tracks>
			<wheels>
				<lodDist>MEDIUM</lodDist>
				<group>
					<isLeft>true</isLeft>
					<template>W_L</template>
					<radius>
						0.19
						<!--BW_String-->
					</radius>
					<startIndex>0</startIndex>
					<count>12</count>
				</group>
				<group>
					<isLeft>false</isLeft>
					<template>W_R</template>
					<radius>
						0.19
						<!--BW_String-->
					</radius>
					<startIndex>0</startIndex>
					<count>12</count>
				</group>
				<wheel>
					<isLeft>true</isLeft>
					<isLeading>true</isLeading>
					<name>WD_L0</name>
					<radius>
						0.42
						<!--BW_String-->
					</radius>
					<syncAngle>
						21.1765
						<!--BW_String-->
					</syncAngle>
				</wheel>
				<group>
					<isLeft>true</isLeft>
					<template>WD_L</template>
					<radius>
						0.16
						<!--BW_String-->
					</radius>
					<startIndex>1</startIndex>
					<count>4</count>
				</group>
				<wheel>
					<isLeft>true</isLeft>
					<isLeading>true</isLeading>
					<name>WD_L5</name>
					<radius>
						0.425
						<!--BW_String-->
					</radius>
					<syncAngle>
						21.1765
						<!--BW_String-->
					</syncAngle>
				</wheel>
				<wheel>
					<isLeft>false</isLeft>
					<isLeading>true</isLeading>
					<name>WD_R0</name>
					<radius>
						0.42
						<!--BW_String-->
					</radius>
					<syncAngle>
						21.1765
						<!--BW_String-->
					</syncAngle>
				</wheel>
				<group>
					<isLeft>false</isLeft>
					<template>WD_R</template>
					<radius>
						0.16
						<!--BW_String-->
					</radius>
					<startIndex>1</startIndex>
					<count>4</count>
				</group>
				<wheel>
					<isLeft>false</isLeft>
					<isLeading>true</isLeading>
					<name>WD_R5</name>
					<radius>
						0.425
						<!--BW_String-->
					</radius>
					<syncAngle>
						21.1765
						<!--BW_String-->
					</syncAngle>
				</wheel>
			</wheels>
			<drivingWheels>WD_L0 WD_L5</drivingWheels>
			<effects>
				<lodDist>MEDIUM</lodDist>
				<dust>mediumTankDust</dust>
				<mud>mediumTankMud</mud>
			</effects>
			<wwsoundPC>treads_type_pc</wwsoundPC>
			<wwsoundNPC>trds_med_npc</wwsoundNPC>
			<hullPosition>
				0.000000 1.1442 0.000000
				<!--BW_String-->
			</hullPosition>
			<hitTester>
				<collisionModelServer>vehicles/russian/R06_T-28/collision/Chassis.model</collisionModelServer>
				<collisionModelClient>vehicles/russian/R06_T-28/collision_client/Chassis.model</collisionModelClient>
			</hitTester>
			<topRightCarryingPoint>
				1.23882 2.5897
				<!--BW_String-->
			</topRightCarryingPoint>
			<maxClimbAngle>25</maxClimbAngle>
			<navmeshGirth>
				6.0
				<!--BW_String-->
			</navmeshGirth>
			<AODecals>
				<decal>
					<transform>
						<row0>3.921320 0.000000 0.000000</row0>
						<row1>-0.000000 1.758900 0.000000</row1>
						<row2>-0.000000 0.000000 9.627260</row2>
						<row3>-0.000000 0.000000 0.000000</row3>
					</transform>
				</decal>
			</AODecals>
			<groundNodes>
				<group>
					<template>Track_L</template>
					<startIndex>0</startIndex>
					<count>12</count>
					<isLeft>true</isLeft>
					<minOffset>
						-0.1
						<!--BW_String-->
					</minOffset>
					<maxOffset>
						0.07
						<!--BW_String-->
					</maxOffset>
				</group>
				<group>
					<template>Track_R</template>
					<startIndex>0</startIndex>
					<count>12</count>
					<isLeft>false</isLeft>
					<minOffset>
						-0.1
						<!--BW_String-->
					</minOffset>
					<maxOffset>
						0.07
						<!--BW_String-->
					</maxOffset>
				</group>
			</groundNodes>
			<splineDesc>
				<segmentModelLeft>vehicles/russian/R06_T-28/track/segment.model</segmentModelLeft>
				<segmentModelRight>vehicles/russian/R06_T-28/track/segment.model</segmentModelRight>
				<left>vehicles/russian/R06_T-28/track/left.track</left>
				<right>vehicles/russian/R06_T-28/track/right.track</right>
				<segmentLength>
					0.132
					<!--BW_String-->
				</segmentLength>
				<segmentOffset>
					0.223
					<!--BW_String-->
				</segmentOffset>
				<lodDist>MEDIUM</lodDist>
				<atlas>
					<UTiles>1</UTiles>
					<VTiles>1</VTiles>
				</atlas>
			</splineDesc>
			<trackNodes>
				<enable>true</enable>
				<linkBones>false</linkBones>
				<maxAmplitude>
					0.015
					<!--BW_String-->
				</maxAmplitude>
				<maxOffset>
					0.01
					<!--BW_String-->
				</maxOffset>
				<gravity>-9</gravity>
				<elasticity>757</elasticity>
				<damping>2</damping>
				<forwardElastK>1</forwardElastK>
				<backwardElastK>1</backwardElastK>
				<offset>0.000000</offset>
				<node>
					<isLeft>true</isLeft>
					<name>Track_VT_L0</name>
					<forwardElastK>
						0.85
						<!--BW_String-->
					</forwardElastK>
					<backwardElastK>
						1.6
						<!--BW_String-->
					</backwardElastK>
					<offset>
						-0.099
						<!--BW_String-->
					</offset>
				</node>
				<node>
					<isLeft>false</isLeft>
					<name>Track_VT_R0</name>
					<forwardElastK>
						0.85
						<!--BW_String-->
					</forwardElastK>
					<backwardElastK>
						1.6
						<!--BW_String-->
					</backwardElastK>
					<offset>
						-0.099
						<!--BW_String-->
					</offset>
				</node>
				<node>
					<isLeft>true</isLeft>
					<name>Track_VT_L1</name>
					<forwardElastK>
						0.83
						<!--BW_String-->
					</forwardElastK>
					<backwardElastK>2</backwardElastK>
					<offset>
						-0.027
						<!--BW_String-->
					</offset>
				</node>
				<node>
					<isLeft>true</isLeft>
					<name>Track_VT_L2</name>
					<forwardElastK>
						0.8
						<!--BW_String-->
					</forwardElastK>
					<backwardElastK>
						2.5
						<!--BW_String-->
					</backwardElastK>
					<offset>
						-0.039
						<!--BW_String-->
					</offset>
				</node>
				<node>
					<isLeft>true</isLeft>
					<name>Track_VT_L3</name>
					<forwardElastK>
						0.8
						<!--BW_String-->
					</forwardElastK>
					<backwardElastK>3</backwardElastK>
					<offset>
						-0.044
						<!--BW_String-->
					</offset>
				</node>
				<node>
					<isLeft>true</isLeft>
					<name>Track_VT_L4</name>
					<elasticity>1105</elasticity>
					<forwardElastK>
						0.8
						<!--BW_String-->
					</forwardElastK>
					<backwardElastK>
						3.5
						<!--BW_String-->
					</backwardElastK>
					<offset>
						-0.099
						<!--BW_String-->
					</offset>
				</node>
				<node>
					<isLeft>false</isLeft>
					<name>Track_VT_R1</name>
					<forwardElastK>
						0.83
						<!--BW_String-->
					</forwardElastK>
					<backwardElastK>2</backwardElastK>
					<offset>
						-0.027
						<!--BW_String-->
					</offset>
				</node>
				<node>
					<isLeft>false</isLeft>
					<name>Track_VT_R2</name>
					<forwardElastK>
						0.8
						<!--BW_String-->
					</forwardElastK>
					<backwardElastK>
						2.5
						<!--BW_String-->
					</backwardElastK>
					<offset>
						-0.039
						<!--BW_String-->
					</offset>
				</node>
				<node>
					<isLeft>false</isLeft>
					<name>Track_VT_R3</name>
					<forwardElastK>
						0.8
						<!--BW_String-->
					</forwardElastK>
					<backwardElastK>3</backwardElastK>
					<offset>
						-0.044
						<!--BW_String-->
					</offset>
				</node>
				<node>
					<isLeft>false</isLeft>
					<name>Track_VT_R4</name>
					<elasticity>1105</elasticity>
					<forwardElastK>
						0.8
						<!--BW_String-->
					</forwardElastK>
					<backwardElastK>
						3.5
						<!--BW_String-->
					</backwardElastK>
					<offset>
						-0.099
						<!--BW_String-->
					</offset>
				</node>
				<node>
					<isLeft>true</isLeft>
					<name>Track_VD_L0</name>
					<forwardElastK>
						1.13
						<!--BW_String-->
					</forwardElastK>
					<backwardElastK>
						1.5
						<!--BW_String-->
					</backwardElastK>
					<offset>
						-0.03
						<!--BW_String-->
					</offset>
				</node>
				<node>
					<isLeft>false</isLeft>
					<name>Track_VD_R0</name>
					<forwardElastK>
						0.88
						<!--BW_String-->
					</forwardElastK>
					<backwardElastK>
						1.5
						<!--BW_String-->
					</backwardElastK>
					<offset>
						-0.03
						<!--BW_String-->
					</offset>
				</node>
				<node>
					<isLeft>true</isLeft>
					<name>Track_VD_L1</name>
					<forwardElastK>
						2.05
						<!--BW_String-->
					</forwardElastK>
					<backwardElastK>
						1.39
						<!--BW_String-->
					</backwardElastK>
					<offset>
						-0.03
						<!--BW_String-->
					</offset>
				</node>
				<node>
					<isLeft>false</isLeft>
					<name>Track_VD_R1</name>
					<forwardElastK>
						2.05
						<!--BW_String-->
					</forwardElastK>
					<backwardElastK>
						0.8
						<!--BW_String-->
					</backwardElastK>
					<offset>
						-0.03
						<!--BW_String-->
					</offset>
				</node>
			</trackNodes>
			<trackThickness>0.000000</trackThickness>
		</T-28_A>
	</chassis>
	<turrets0>
		<T-28_cylindrical>
			<userString>#ussr_vehicles:T-28_cylindrical</userString>
			<shortUserString>#ussr_vehicles:T-28_cylindrical_short</shortUserString>
			<tags/>
			<level>3</level>
			<price>
				2160.0
				<!--BW_String-->
			</price>
			<unlocks>
				<turret>
					T-28_conic
					<cost>1025</cost>
				</turret>
			</unlocks>
			<armor>
				<armor_1>20</armor_1>
				<armor_2>15</armor_2>
				<armor_3>20</armor_3>
				<armor_4>20</armor_4>
				<armor_5>15</armor_5>
				<armor_6>15</armor_6>
				<armor_7>20</armor_7>
				<armor_8>0</armor_8>
				<armor_9>
					10
					<vehicleDamageFactor>
						0.0
						<!--BW_String-->
					</vehicleDamageFactor>
				</armor_9>
			</armor>
			<primaryArmor>armor_1 armor_3 armor_4</primaryArmor>
			<weight>2000</weight>
			<maxHealth>64</maxHealth>
			<rotationSpeed>46</rotationSpeed>
			<turretRotatorHealth>
				<maxHealth>80</maxHealth>
				<maxRegenHealth>40</maxRegenHealth>
				<repairCost>
					1.0
					<!--BW_String-->
				</repairCost>
			</turretRotatorHealth>
			<circularVisionRadius>320</circularVisionRadius>
			<surveyingDeviceHealth>
				<maxHealth>60</maxHealth>
				<maxRegenHealth>30</maxRegenHealth>
				<repairCost>
					1.0
					<!--BW_String-->
				</repairCost>
			</surveyingDeviceHealth>
			<guns>
				<_76mm_KT-28>
					shared
					<maxAmmo>69</maxAmmo>
					<unlocks>
						<gun>
							_76mm_L-10
							<cost>
								400.0
								<!--BW_String-->
							</cost>
						</gun>
						<gun>
							_57mm_ZiS-8
							<cost>550</cost>
						</gun>
					</unlocks>
					<armor>
						<armor_1>
							20
							<vehicleDamageFactor>
								0.0
								<!--BW_String-->
							</vehicleDamageFactor>
						</armor_1>
						<armor_2>
							10
							<vehicleDamageFactor>
								0.0
								<!--BW_String-->
							</vehicleDamageFactor>
						</armor_2>
						<armor_3>
							20
							<vehicleDamageFactor>
								0.0
								<!--BW_String-->
							</vehicleDamageFactor>
						</armor_3>
						<armor_4>
							0
							<vehicleDamageFactor>
								0.0
								<!--BW_String-->
							</vehicleDamageFactor>
						</armor_4>
						<armor_5>
							15
							<vehicleDamageFactor>
								0.0
								<!--BW_String-->
							</vehicleDamageFactor>
						</armor_5>
						<armor_6>
							15
							<vehicleDamageFactor>
								0.0
								<!--BW_String-->
							</vehicleDamageFactor>
						</armor_6>
						<armor_7>
							15
							<vehicleDamageFactor>
								0.0
								<!--BW_String-->
							</vehicleDamageFactor>
						</armor_7>
						<gun>20</gun>
					</armor>
					<shotDispersionRadius>
						0.6
						<!--BW_String-->
					</shotDispersionRadius>
					<reloadTime>
						4.6
						<!--BW_String-->
					</reloadTime>
					<shotDispersionFactors>
						<turretRotation>
							0.18
							<!--BW_String-->
						</turretRotation>
						<afterShot>
							4.0
							<!--BW_String-->
						</afterShot>
						<whileGunDamaged>
							2.0
							<!--BW_String-->
						</whileGunDamaged>
					</shotDispersionFactors>
					<aimingTime>
						2.3
						<!--BW_String-->
					</aimingTime>
					<pitchLimits>
						<minPitch>0 -25 1 -25</minPitch>
						<maxPitch>
							0 6 0.353005 6 0.416667 3 0.583333 3 0.646995 6 1 6
							<!--BW_String-->
						</maxPitch>
					</pitchLimits>
					<invisibilityFactorAtShot>
						0.26
						<!--BW_String-->
					</invisibilityFactorAtShot>
					<models>
						<undamaged>vehicles/russian/R06_T-28/normal/lod0/Gun_01.model</undamaged>
						<destroyed>vehicles/russian/R06_T-28/crash/lod0/Gun_01.model</destroyed>
						<exploded>vehicles/russian/R06_T-28/crash/lod0/Gun_01.model</exploded>
					</models>
					<hitTester>
						<collisionModelServer>vehicles/russian/R06_T-28/collision/Gun_01.model</collisionModelServer>
						<collisionModelClient>vehicles/russian/R06_T-28/collision_client/Gun_01.model</collisionModelClient>
					</hitTester>
				</_76mm_KT-28>
				<_57mm_ZiS-8>
					shared
					<maxAmmo>78</maxAmmo>
					<pitchLimits>
						<minPitch>0 -25 1 -25</minPitch>
						<maxPitch>
							0 6 0.339116 6 0.402778 5 0.597222 5 0.660884 6 1 6
							<!--BW_String-->
						</maxPitch>
					</pitchLimits>
					<unlocks>
						<gun>
							_57mm_ZiS-4
							<cost>
								2200.0
								<!--BW_String-->
							</cost>
						</gun>
					</unlocks>
					<armor>
						<armor_1>
							20
							<vehicleDamageFactor>
								0.0
								<!--BW_String-->
							</vehicleDamageFactor>
						</armor_1>
						<armor_3>
							20
							<vehicleDamageFactor>
								0.0
								<!--BW_String-->
							</vehicleDamageFactor>
						</armor_3>
						<armor_4>
							0
							<vehicleDamageFactor>
								0.0
								<!--BW_String-->
							</vehicleDamageFactor>
						</armor_4>
						<armor_5>
							15
							<vehicleDamageFactor>
								0.0
								<!--BW_String-->
							</vehicleDamageFactor>
						</armor_5>
						<armor_6>
							15
							<vehicleDamageFactor>
								0.0
								<!--BW_String-->
							</vehicleDamageFactor>
						</armor_6>
						<gun>10</gun>
					</armor>
					<shotDispersionRadius>
						0.45
						<!--BW_String-->
					</shotDispersionRadius>
					<reloadTime>
						2.9
						<!--BW_String-->
					</reloadTime>
					<shotDispersionFactors>
						<turretRotation>
							0.18
							<!--BW_String-->
						</turretRotation>
						<afterShot>
							4.0
							<!--BW_String-->
						</afterShot>
						<whileGunDamaged>
							2.0
							<!--BW_String-->
						</whileGunDamaged>
					</shotDispersionFactors>
					<aimingTime>
						2.3
						<!--BW_String-->
					</aimingTime>
					<invisibilityFactorAtShot>
						0.28
						<!--BW_String-->
					</invisibilityFactorAtShot>
					<models>
						<undamaged>vehicles/russian/R06_T-28/normal/lod0/Gun_04.model</undamaged>
						<destroyed>vehicles/russian/R06_T-28/crash/lod0/Gun_04.model</destroyed>
						<exploded>vehicles/russian/R06_T-28/crash/lod0/Gun_04.model</exploded>
					</models>
					<hitTester>
						<collisionModelServer>vehicles/russian/R06_T-28/collision/Gun_04.model</collisionModelServer>
						<collisionModelClient>vehicles/russian/R06_T-28/collision_client/Gun_04.model</collisionModelClient>
					</hitTester>
					<camouflage>
						<tiling>
							1.3 1.3 0.000000 0.000000
							<!--BW_String-->
						</tiling>
					</camouflage>
				</_57mm_ZiS-8>
				<_76mm_L-10>
					shared
					<maxAmmo>69</maxAmmo>
					<unlocks>
						<gun>
							_76mm_F-32
							<cost>500</cost>
						</gun>
					</unlocks>
					<armor>
						<armor_1>
							20
							<vehicleDamageFactor>
								0.0
								<!--BW_String-->
							</vehicleDamageFactor>
						</armor_1>
						<armor_2>
							20
							<vehicleDamageFactor>
								0.0
								<!--BW_String-->
							</vehicleDamageFactor>
						</armor_2>
						<armor_3>
							20
							<vehicleDamageFactor>
								0.0
								<!--BW_String-->
							</vehicleDamageFactor>
						</armor_3>
						<armor_4>
							0
							<vehicleDamageFactor>
								0.0
								<!--BW_String-->
							</vehicleDamageFactor>
						</armor_4>
						<armor_5>
							15
							<vehicleDamageFactor>
								0.0
								<!--BW_String-->
							</vehicleDamageFactor>
						</armor_5>
						<armor_6>
							15
							<vehicleDamageFactor>
								0.0
								<!--BW_String-->
							</vehicleDamageFactor>
						</armor_6>
						<gun>20</gun>
					</armor>
					<shotDispersionRadius>
						0.57
						<!--BW_String-->
					</shotDispersionRadius>
					<reloadTime>
						4.6
						<!--BW_String-->
					</reloadTime>
					<shotDispersionFactors>
						<turretRotation>
							0.18
							<!--BW_String-->
						</turretRotation>
						<afterShot>
							4.0
							<!--BW_String-->
						</afterShot>
						<whileGunDamaged>
							2.0
							<!--BW_String-->
						</whileGunDamaged>
					</shotDispersionFactors>
					<aimingTime>
						2.9
						<!--BW_String-->
					</aimingTime>
					<pitchLimits>
						<minPitch>0 -25 1 -25</minPitch>
						<maxPitch>
							0 6 0.339116 6 0.402778 2 0.597222 2 0.660884 6 1 6
							<!--BW_String-->
						</maxPitch>
					</pitchLimits>
					<invisibilityFactorAtShot>
						0.26
						<!--BW_String-->
					</invisibilityFactorAtShot>
					<models>
						<undamaged>vehicles/russian/R06_T-28/normal/lod0/Gun_02.model</undamaged>
						<destroyed>vehicles/russian/R06_T-28/crash/lod0/Gun_02.model</destroyed>
						<exploded>vehicles/russian/R06_T-28/crash/lod0/Gun_02.model</exploded>
					</models>
					<hitTester>
						<collisionModelServer>vehicles/russian/R06_T-28/collision/Gun_02.model</collisionModelServer>
						<collisionModelClient>vehicles/russian/R06_T-28/collision_client/Gun_02.model</collisionModelClient>
					</hitTester>
					<camouflage>
						<tiling>
							0.94 0.94 0.000000 0.000000
							<!--BW_String-->
						</tiling>
					</camouflage>
				</_76mm_L-10>
				<_76mm_F-32>
					shared
					<maxAmmo>69</maxAmmo>
					<armor>
						<armor_1>
							20
							<vehicleDamageFactor>
								0.0
								<!--BW_String-->
							</vehicleDamageFactor>
						</armor_1>
						<armor_2>
							20
							<vehicleDamageFactor>
								0.0
								<!--BW_String-->
							</vehicleDamageFactor>
						</armor_2>
						<armor_3>
							20
							<vehicleDamageFactor>
								0.0
								<!--BW_String-->
							</vehicleDamageFactor>
						</armor_3>
						<armor_4>
							0
							<vehicleDamageFactor>
								0.0
								<!--BW_String-->
							</vehicleDamageFactor>
						</armor_4>
						<armor_5>
							15
							<vehicleDamageFactor>
								0.0
								<!--BW_String-->
							</vehicleDamageFactor>
						</armor_5>
						<armor_6>
							15
							<vehicleDamageFactor>
								0.0
								<!--BW_String-->
							</vehicleDamageFactor>
						</armor_6>
						<armor_7>
							15
							<vehicleDamageFactor>
								0.0
								<!--BW_String-->
							</vehicleDamageFactor>
						</armor_7>
						<gun>20</gun>
					</armor>
					<shotDispersionRadius>
						0.51
						<!--BW_String-->
					</shotDispersionRadius>
					<reloadTime>
						3.9
						<!--BW_String-->
					</reloadTime>
					<shotDispersionFactors>
						<turretRotation>
							0.18
							<!--BW_String-->
						</turretRotation>
						<afterShot>
							4.0
							<!--BW_String-->
						</afterShot>
						<whileGunDamaged>
							2.0
							<!--BW_String-->
						</whileGunDamaged>
					</shotDispersionFactors>
					<aimingTime>
						2.9
						<!--BW_String-->
					</aimingTime>
					<pitchLimits>
						<minPitch>0 -25 1 -25</minPitch>
						<maxPitch>
							0 6 0.319671 6 0.383333 -2 0.616667 -2 0.680329 6 1 6
							<!--BW_String-->
						</maxPitch>
					</pitchLimits>
					<invisibilityFactorAtShot>
						0.26
						<!--BW_String-->
					</invisibilityFactorAtShot>
					<models>
						<undamaged>vehicles/russian/R06_T-28/normal/lod0/Gun_03.model</undamaged>
						<destroyed>vehicles/russian/R06_T-28/crash/lod0/Gun_03.model</destroyed>
						<exploded>vehicles/russian/R06_T-28/crash/lod0/Gun_03.model</exploded>
					</models>
					<hitTester>
						<collisionModelServer>vehicles/russian/R06_T-28/collision/Gun_03.model</collisionModelServer>
						<collisionModelClient>vehicles/russian/R06_T-28/collision_client/Gun_03.model</collisionModelClient>
					</hitTester>
					<camouflage>
						<tiling>
							1.54 1.54 0.000000 0.000000
							<!--BW_String-->
						</tiling>
					</camouflage>
				</_76mm_F-32>
				<_57mm_ZiS-4>
					shared
					<maxAmmo>78</maxAmmo>
					<pitchLimits>
						<minPitch>0 -25 1 -25</minPitch>
						<maxPitch>
							0 6 0.339116 6 0.402778 5 0.597222 5 0.660884 6 1 6
							<!--BW_String-->
						</maxPitch>
					</pitchLimits>
					<reloadTime>
						2.7
						<!--BW_String-->
					</reloadTime>
					<armor>
						<armor_1>
							20
							<vehicleDamageFactor>
								0.0
								<!--BW_String-->
							</vehicleDamageFactor>
						</armor_1>
						<armor_3>
							20
							<vehicleDamageFactor>
								0.0
								<!--BW_String-->
							</vehicleDamageFactor>
						</armor_3>
						<armor_4>
							0
							<vehicleDamageFactor>
								0.0
								<!--BW_String-->
							</vehicleDamageFactor>
						</armor_4>
						<armor_5>
							15
							<vehicleDamageFactor>
								0.0
								<!--BW_String-->
							</vehicleDamageFactor>
						</armor_5>
						<armor_6>
							15
							<vehicleDamageFactor>
								0.0
								<!--BW_String-->
							</vehicleDamageFactor>
						</armor_6>
						<gun>10</gun>
					</armor>
					<shotDispersionRadius>
						0.34
						<!--BW_String-->
					</shotDispersionRadius>
					<shotDispersionFactors>
						<turretRotation>
							0.18
							<!--BW_String-->
						</turretRotation>
						<afterShot>
							4.0
							<!--BW_String-->
						</afterShot>
						<whileGunDamaged>
							2.0
							<!--BW_String-->
						</whileGunDamaged>
					</shotDispersionFactors>
					<aimingTime>
						2.3
						<!--BW_String-->
					</aimingTime>
					<invisibilityFactorAtShot>
						0.266
						<!--BW_String-->
					</invisibilityFactorAtShot>
					<models>
						<undamaged>vehicles/russian/R06_T-28/normal/lod0/Gun_05.model</undamaged>
						<destroyed>vehicles/russian/R06_T-28/crash/lod0/Gun_05.model</destroyed>
						<exploded>vehicles/russian/R06_T-28/crash/lod0/Gun_05.model</exploded>
					</models>
					<hitTester>
						<collisionModelServer>vehicles/russian/R06_T-28/collision/Gun_05.model</collisionModelServer>
						<collisionModelClient>vehicles/russian/R06_T-28/collision_client/Gun_05.model</collisionModelClient>
					</hitTester>
					<camouflage>
						<tiling>
							1.24 1.24 0.000000 0.000000
							<!--BW_String-->
						</tiling>
					</camouflage>
				</_57mm_ZiS-4>
			</guns>
			<models>
				<undamaged>vehicles/russian/R06_T-28/normal/lod0/Turret_01.model</undamaged>
				<destroyed>vehicles/russian/R06_T-28/crash/lod0/Turret_01.model</destroyed>
				<exploded>vehicles/russian/R06_T-28/crash/lod0/Turret_01.model</exploded>
			</models>
			<hitTester>
				<collisionModelServer>vehicles/russian/R06_T-28/collision/Turret_01.model</collisionModelServer>
				<collisionModelClient>vehicles/russian/R06_T-28/collision_client/Turret_01.model</collisionModelClient>
			</hitTester>
			<gunPosition>
				0.000000 0.44668 0.83599
				<!--BW_String-->
			</gunPosition>
			<emblemSlots>
				<player>
					<rayStart>0.804964 0.445527 -0.694605</rayStart>
					<rayEnd>0.616031 0.445489 -0.628997</rayEnd>
					<rayUp>
						0.000000 1 0.000000
						<!--BW_String-->
					</rayUp>
					<size>
						0.32
						<!--BW_String-->
					</size>
					<hideIfDamaged>false</hideIfDamaged>
					<isMirrored>true</isMirrored>
				</player>
				<player>
					<rayStart>-0.804964 0.445527 -0.694605</rayStart>
					<rayEnd>-0.616031 0.445489 -0.628997</rayEnd>
					<rayUp>
						0.000000 1 0.000000
						<!--BW_String-->
					</rayUp>
					<size>
						0.32
						<!--BW_String-->
					</size>
					<hideIfDamaged>false</hideIfDamaged>
				</player>
			</emblemSlots>
			<showEmblemsOnGun>false</showEmblemsOnGun>
			<physicsShape>
				0.952 0.000 1.000 0.000 0.400 0.326 0.714 0.614 0.542 0.500 0.000 0.500 0.000 0.100 0.000
				<!--BW_String-->
			</physicsShape>
			<wwturretRotatorSoundManual>tur_mech_trav</wwturretRotatorSoundManual>
		</T-28_cylindrical>
		<T-28_conic>
			<userString>#ussr_vehicles:T-28_conic</userString>
			<shortUserString>#ussr_vehicles:T-28_conic_short</shortUserString>
			<tags/>
			<level>4</level>
			<price>
				4370.0
				<!--BW_String-->
			</price>
			<armor>
				<armor_1>25</armor_1>
				<armor_2>
					10
					<vehicleDamageFactor>
						0.0
						<!--BW_String-->
					</vehicleDamageFactor>
				</armor_2>
				<armor_3>25</armor_3>
				<armor_4>25</armor_4>
				<armor_5>15</armor_5>
				<armor_6>15</armor_6>
				<armor_7>25</armor_7>
				<armor_8>0</armor_8>
			</armor>
			<primaryArmor>armor_1 armor_3 armor_4</primaryArmor>
			<weight>2500</weight>
			<maxHealth>94</maxHealth>
			<rotationSpeed>44</rotationSpeed>
			<turretRotatorHealth>
				<maxHealth>80</maxHealth>
				<maxRegenHealth>40</maxRegenHealth>
				<repairCost>
					1.0
					<!--BW_String-->
				</repairCost>
			</turretRotatorHealth>
			<circularVisionRadius>340</circularVisionRadius>
			<surveyingDeviceHealth>
				<maxHealth>60</maxHealth>
				<maxRegenHealth>30</maxRegenHealth>
				<repairCost>
					1.0
					<!--BW_String-->
				</repairCost>
			</surveyingDeviceHealth>
			<guns>
				<_76mm_KT-28>
					shared
					<maxAmmo>69</maxAmmo>
					<armor>
						<armor_1>
							25
							<vehicleDamageFactor>
								0.0
								<!--BW_String-->
							</vehicleDamageFactor>
						</armor_1>
						<armor_2>
							10
							<vehicleDamageFactor>
								0.0
								<!--BW_String-->
							</vehicleDamageFactor>
						</armor_2>
						<armor_3>
							25
							<vehicleDamageFactor>
								0.0
								<!--BW_String-->
							</vehicleDamageFactor>
						</armor_3>
						<armor_4>
							0
							<vehicleDamageFactor>
								0.0
								<!--BW_String-->
							</vehicleDamageFactor>
						</armor_4>
						<armor_5>
							15
							<vehicleDamageFactor>
								0.0
								<!--BW_String-->
							</vehicleDamageFactor>
						</armor_5>
						<armor_6>
							15
							<vehicleDamageFactor>
								0.0
								<!--BW_String-->
							</vehicleDamageFactor>
						</armor_6>
						<armor_7>
							15
							<vehicleDamageFactor>
								0.0
								<!--BW_String-->
							</vehicleDamageFactor>
						</armor_7>
						<gun>20</gun>
					</armor>
					<shotDispersionRadius>
						0.6
						<!--BW_String-->
					</shotDispersionRadius>
					<reloadTime>
						4.6
						<!--BW_String-->
					</reloadTime>
					<aimingTime>
						2.3
						<!--BW_String-->
					</aimingTime>
					<pitchLimits>
						<minPitch>0 -25 1 -25</minPitch>
						<maxPitch>
							0 6 0.353005 6 0.416667 3 0.583333 3 0.646995 6 1 6
							<!--BW_String-->
						</maxPitch>
					</pitchLimits>
					<invisibilityFactorAtShot>
						0.26
						<!--BW_String-->
					</invisibilityFactorAtShot>
					<models>
						<undamaged>vehicles/russian/R06_T-28/normal/lod0/Gun_06.model</undamaged>
						<destroyed>vehicles/russian/R06_T-28/crash/lod0/Gun_06.model</destroyed>
						<exploded>vehicles/russian/R06_T-28/crash/lod0/Gun_06.model</exploded>
					</models>
					<hitTester>
						<collisionModelServer>vehicles/russian/R06_T-28/collision/Gun_06.model</collisionModelServer>
						<collisionModelClient>vehicles/russian/R06_T-28/collision_client/Gun_06.model</collisionModelClient>
					</hitTester>
				</_76mm_KT-28>
				<_57mm_ZiS-8>
					shared
					<maxAmmo>78</maxAmmo>
					<pitchLimits>
						<minPitch>0 -25 1 -25</minPitch>
						<maxPitch>
							0 6 0.339116 6 0.402778 5 0.597222 5 0.660884 6 1 6
							<!--BW_String-->
						</maxPitch>
					</pitchLimits>
					<armor>
						<armor_1>
							25
							<vehicleDamageFactor>
								0.0
								<!--BW_String-->
							</vehicleDamageFactor>
						</armor_1>
						<armor_3>
							25
							<vehicleDamageFactor>
								0.0
								<!--BW_String-->
							</vehicleDamageFactor>
						</armor_3>
						<armor_4>
							0
							<vehicleDamageFactor>
								0.0
								<!--BW_String-->
							</vehicleDamageFactor>
						</armor_4>
						<armor_5>
							15
							<vehicleDamageFactor>
								0.0
								<!--BW_String-->
							</vehicleDamageFactor>
						</armor_5>
						<armor_6>
							15
							<vehicleDamageFactor>
								0.0
								<!--BW_String-->
							</vehicleDamageFactor>
						</armor_6>
						<gun>10</gun>
					</armor>
					<shotDispersionRadius>
						0.45
						<!--BW_String-->
					</shotDispersionRadius>
					<reloadTime>
						2.9
						<!--BW_String-->
					</reloadTime>
					<aimingTime>
						2.3
						<!--BW_String-->
					</aimingTime>
					<invisibilityFactorAtShot>
						0.28
						<!--BW_String-->
					</invisibilityFactorAtShot>
					<models>
						<undamaged>vehicles/russian/R06_T-28/normal/lod0/Gun_09.model</undamaged>
						<destroyed>vehicles/russian/R06_T-28/crash/lod0/Gun_09.model</destroyed>
						<exploded>vehicles/russian/R06_T-28/crash/lod0/Gun_09.model</exploded>
					</models>
					<hitTester>
						<collisionModelServer>vehicles/russian/R06_T-28/collision/Gun_09.model</collisionModelServer>
						<collisionModelClient>vehicles/russian/R06_T-28/collision_client/Gun_09.model</collisionModelClient>
					</hitTester>
					<camouflage>
						<tiling>
							0.94 0.94 0.000000 0.000000
							<!--BW_String-->
						</tiling>
					</camouflage>
				</_57mm_ZiS-8>
				<_76mm_L-10>
					shared
					<maxAmmo>69</maxAmmo>
					<armor>
						<armor_1>
							25
							<vehicleDamageFactor>
								0.0
								<!--BW_String-->
							</vehicleDamageFactor>
						</armor_1>
						<armor_2>
							25
							<vehicleDamageFactor>
								0.0
								<!--BW_String-->
							</vehicleDamageFactor>
						</armor_2>
						<armor_3>
							25
							<vehicleDamageFactor>
								0.0
								<!--BW_String-->
							</vehicleDamageFactor>
						</armor_3>
						<armor_4>
							0
							<vehicleDamageFactor>
								0.0
								<!--BW_String-->
							</vehicleDamageFactor>
						</armor_4>
						<armor_5>
							15
							<vehicleDamageFactor>
								0.0
								<!--BW_String-->
							</vehicleDamageFactor>
						</armor_5>
						<armor_6>
							15
							<vehicleDamageFactor>
								0.0
								<!--BW_String-->
							</vehicleDamageFactor>
						</armor_6>
						<gun>20</gun>
					</armor>
					<shotDispersionRadius>
						0.57
						<!--BW_String-->
					</shotDispersionRadius>
					<reloadTime>
						4.6
						<!--BW_String-->
					</reloadTime>
					<aimingTime>
						2.9
						<!--BW_String-->
					</aimingTime>
					<pitchLimits>
						<minPitch>0 -25 1 -25</minPitch>
						<maxPitch>
							0 6 0.339116 6 0.402778 2 0.597222 2 0.660884 6 1 6
							<!--BW_String-->
						</maxPitch>
					</pitchLimits>
					<invisibilityFactorAtShot>
						0.26
						<!--BW_String-->
					</invisibilityFactorAtShot>
					<models>
						<undamaged>vehicles/russian/R06_T-28/normal/lod0/Gun_07.model</undamaged>
						<destroyed>vehicles/russian/R06_T-28/crash/lod0/Gun_07.model</destroyed>
						<exploded>vehicles/russian/R06_T-28/crash/lod0/Gun_07.model</exploded>
					</models>
					<hitTester>
						<collisionModelServer>vehicles/russian/R06_T-28/collision/Gun_07.model</collisionModelServer>
						<collisionModelClient>vehicles/russian/R06_T-28/collision_client/Gun_07.model</collisionModelClient>
					</hitTester>
				</_76mm_L-10>
				<_76mm_F-32>
					shared
					<maxAmmo>69</maxAmmo>
					<armor>
						<armor_1>
							25
							<vehicleDamageFactor>
								0.0
								<!--BW_String-->
							</vehicleDamageFactor>
						</armor_1>
						<armor_2>
							25
							<vehicleDamageFactor>
								0.0
								<!--BW_String-->
							</vehicleDamageFactor>
						</armor_2>
						<armor_3>
							25
							<vehicleDamageFactor>
								0.0
								<!--BW_String-->
							</vehicleDamageFactor>
						</armor_3>
						<armor_4>
							0
							<vehicleDamageFactor>
								0.0
								<!--BW_String-->
							</vehicleDamageFactor>
						</armor_4>
						<armor_5>
							15
							<vehicleDamageFactor>
								0.0
								<!--BW_String-->
							</vehicleDamageFactor>
						</armor_5>
						<armor_6>
							15
							<vehicleDamageFactor>
								0.0
								<!--BW_String-->
							</vehicleDamageFactor>
						</armor_6>
						<armor_7>
							15
							<vehicleDamageFactor>
								0.0
								<!--BW_String-->
							</vehicleDamageFactor>
						</armor_7>
						<gun>20</gun>
					</armor>
					<shotDispersionRadius>
						0.51
						<!--BW_String-->
					</shotDispersionRadius>
					<reloadTime>
						3.9
						<!--BW_String-->
					</reloadTime>
					<aimingTime>
						2.9
						<!--BW_String-->
					</aimingTime>
					<pitchLimits>
						<minPitch>0 -25 1 -25</minPitch>
						<maxPitch>
							0 6 0.319671 6 0.383333 -2 0.616667 -2 0.680329 6 1 6
							<!--BW_String-->
						</maxPitch>
					</pitchLimits>
					<invisibilityFactorAtShot>
						0.26
						<!--BW_String-->
					</invisibilityFactorAtShot>
					<models>
						<undamaged>vehicles/russian/R06_T-28/normal/lod0/Gun_08.model</undamaged>
						<destroyed>vehicles/russian/R06_T-28/crash/lod0/Gun_08.model</destroyed>
						<exploded>vehicles/russian/R06_T-28/crash/lod0/Gun_08.model</exploded>
					</models>
					<hitTester>
						<collisionModelServer>vehicles/russian/R06_T-28/collision/Gun_08.model</collisionModelServer>
						<collisionModelClient>vehicles/russian/R06_T-28/collision_client/Gun_08.model</collisionModelClient>
					</hitTester>
				</_76mm_F-32>
				<_57mm_ZiS-4>
					shared
					<maxAmmo>78</maxAmmo>
					<reloadTime>
						2.7
						<!--BW_String-->
					</reloadTime>
					<pitchLimits>
						<minPitch>0 -25 1 -25</minPitch>
						<maxPitch>
							0 6 0.339116 6 0.402778 5 0.597222 5 0.660884 6 1 6
							<!--BW_String-->
						</maxPitch>
					</pitchLimits>
					<armor>
						<armor_1>
							25
							<vehicleDamageFactor>
								0.0
								<!--BW_String-->
							</vehicleDamageFactor>
						</armor_1>
						<armor_3>
							25
							<vehicleDamageFactor>
								0.0
								<!--BW_String-->
							</vehicleDamageFactor>
						</armor_3>
						<armor_4>
							0
							<vehicleDamageFactor>
								0.0
								<!--BW_String-->
							</vehicleDamageFactor>
						</armor_4>
						<armor_5>
							15
							<vehicleDamageFactor>
								0.0
								<!--BW_String-->
							</vehicleDamageFactor>
						</armor_5>
						<armor_6>
							15
							<vehicleDamageFactor>
								0.0
								<!--BW_String-->
							</vehicleDamageFactor>
						</armor_6>
						<gun>10</gun>
					</armor>
					<shotDispersionRadius>
						0.34
						<!--BW_String-->
					</shotDispersionRadius>
					<aimingTime>
						2.3
						<!--BW_String-->
					</aimingTime>
					<invisibilityFactorAtShot>
						0.266
						<!--BW_String-->
					</invisibilityFactorAtShot>
					<models>
						<undamaged>vehicles/russian/R06_T-28/normal/lod0/Gun_10.model</undamaged>
						<destroyed>vehicles/russian/R06_T-28/crash/lod0/Gun_10.model</destroyed>
						<exploded>vehicles/russian/R06_T-28/crash/lod0/Gun_10.model</exploded>
					</models>
					<hitTester>
						<collisionModelServer>vehicles/russian/R06_T-28/collision/Gun_10.model</collisionModelServer>
						<collisionModelClient>vehicles/russian/R06_T-28/collision_client/Gun_10.model</collisionModelClient>
					</hitTester>
					<camouflage>
						<tiling>
							1.24 1.24 0.000000 0.000000
							<!--BW_String-->
						</tiling>
					</camouflage>
				</_57mm_ZiS-4>
			</guns>
			<models>
				<undamaged>vehicles/russian/R06_T-28/normal/lod0/Turret_02.model</undamaged>
				<destroyed>vehicles/russian/R06_T-28/crash/lod0/Turret_02.model</destroyed>
				<exploded>vehicles/russian/R06_T-28/crash/lod0/Turret_02.model</exploded>
			</models>
			<hitTester>
				<collisionModelServer>vehicles/russian/R06_T-28/collision/Turret_02.model</collisionModelServer>
				<collisionModelClient>vehicles/russian/R06_T-28/collision_client/Turret_02.model</collisionModelClient>
			</hitTester>
			<gunPosition>
				0.000000 0.44668 0.83599
				<!--BW_String-->
			</gunPosition>
			<emblemSlots>
				<player>
					<rayStart>
						0.775351 0.53628 -0.499512
						<!--BW_String-->
					</rayStart>
					<rayEnd>0.585011 0.479896 -0.475195</rayEnd>
					<rayUp>
						0.000000 1 0.000000
						<!--BW_String-->
					</rayUp>
					<size>
						0.32
						<!--BW_String-->
					</size>
					<hideIfDamaged>false</hideIfDamaged>
					<isMirrored>true</isMirrored>
				</player>
				<player>
					<rayStart>
						-0.775351 0.53628 -0.499512
						<!--BW_String-->
					</rayStart>
					<rayEnd>-0.585011 0.479896 -0.475195</rayEnd>
					<rayUp>
						0.000000 1 0.000000
						<!--BW_String-->
					</rayUp>
					<size>
						0.32
						<!--BW_String-->
					</size>
					<hideIfDamaged>false</hideIfDamaged>
				</player>
			</emblemSlots>
			<showEmblemsOnGun>false</showEmblemsOnGun>
			<physicsShape>
				0.958 -0.042 1.000 0.000 0.411 0.326 0.754 0.632 0.444 0.500 0.241 0.500 0.106 0.743 0.000
				<!--BW_String-->
			</physicsShape>
			<wwturretRotatorSoundManual>tur_mech_trav</wwturretRotatorSoundManual>
			<camouflage>
				<tiling>
					0.97 0.97 0.000000 0.000000
					<!--BW_String-->
				</tiling>
			</camouflage>
		</T-28_conic>
	</turrets0>
	<engines>
		<M-5-400>
			shared
			<unlocks>
				<engine>
					M-17T
					<cost>200</cost>
				</engine>
			</unlocks>
		</M-5-400>
		<M-17T>
			shared
			<unlocks>
				<engine>
					M-17F
					<cost>
						850.0
						<!--BW_String-->
					</cost>
				</engine>
			</unlocks>
		</M-17T>
		<M-17F>
			shared
			<unlocks>
				<vehicle>
					R80_KV1
					<cost>13500</cost>
				</vehicle>
			</unlocks>
		</M-17F>
	</engines>
	<fuelTanks>
		<Average>shared</Average>
	</fuelTanks>
	<radios>
		<_71-TK-3>
			shared
			<unlocks>
				<radio>
					_10R
					<cost>
						610.0
						<!--BW_String-->
					</cost>
				</radio>
			</unlocks>
		</_71-TK-3>
		<_10R>shared</_10R>
	</radios>
	<physics>
		<detailed>
			<engines>
				<M-5-400>
					<smplEnginePower>
						422.9124
						<!--BW_String-->
					</smplEnginePower>
				</M-5-400>
				<M-17T>
					<smplEnginePower>
						475.7765
						<!--BW_String-->
					</smplEnginePower>
				</M-17T>
				<M-17F>
					<smplEnginePower>
						528.6406
						<!--BW_String-->
					</smplEnginePower>
				</M-17F>
			</engines>
			<chassis>
				<T-28_0>
					<grounds>
						<ground>
							<medium>
								<rollingFriction>
									0.12075
									<!--BW_String-->
								</rollingFriction>
							</medium>
						</ground>
						<sand>
							<medium>
								<rollingFriction>
									0.12075
									<!--BW_String-->
								</rollingFriction>
							</medium>
						</sand>
						<wood>
							<medium>
								<rollingFriction>
									0.12075
									<!--BW_String-->
								</rollingFriction>
							</medium>
						</wood>
						<snow>
							<medium>
								<rollingFriction>
									0.12075
									<!--BW_String-->
								</rollingFriction>
							</medium>
						</snow>
						<stone>
							<medium>
								<rollingFriction>
									0.12075
									<!--BW_String-->
								</rollingFriction>
							</medium>
						</stone>
						<metal>
							<medium>
								<rollingFriction>
									0.12075
									<!--BW_String-->
								</rollingFriction>
							</medium>
						</metal>
					</grounds>
				</T-28_0>
				<T-28_A>
					<grounds>
						<ground>
							<medium>
								<rollingFriction>
									0.10465
									<!--BW_String-->
								</rollingFriction>
							</medium>
						</ground>
						<sand>
							<medium>
								<rollingFriction>
									0.10465
									<!--BW_String-->
								</rollingFriction>
							</medium>
						</sand>
						<wood>
							<medium>
								<rollingFriction>
									0.10465
									<!--BW_String-->
								</rollingFriction>
							</medium>
						</wood>
						<snow>
							<medium>
								<rollingFriction>
									0.10465
									<!--BW_String-->
								</rollingFriction>
							</medium>
						</snow>
						<stone>
							<medium>
								<rollingFriction>
									0.10465
									<!--BW_String-->
								</rollingFriction>
							</medium>
						</stone>
						<metal>
							<medium>
								<rollingFriction>
									0.10465
									<!--BW_String-->
								</rollingFriction>
							</medium>
						</metal>
					</grounds>
				</T-28_A>
			</chassis>
		</detailed>
	</physics>
	<clientAdjustmentFactors>
		<armour>
			0.843833809
			<!--BW_String-->
		</armour>
	</clientAdjustmentFactors>
	<effects>
		<collision/>
		<damagedStateGroup>large</damagedStateGroup>
	</effects>
	<emblems>
		<default>ussr_star</default>
		<lodDist>MEDIUM</lodDist>
		<alpha>
			0.86
			<!--BW_String-->
		</alpha>
	</emblems>
	<horns>
		<priceFactor>1</priceFactor>
		<distanceFactor>1</distanceFactor>
		<volumeFactor>1</volumeFactor>
	</horns>
</root>
